miprem/__init__.py
miprem/main.py
miprem/merit_profile.css
miprem/merit_profile.py
miprem-0.1.0.dist-info/entry_points.txt
miprem-0.1.0.dist-info/WHEEL
miprem-0.1.0.dist-info/METADATA
miprem-0.1.0.dist-info/RECORD
