Metadata-Version: 2.1
Name: miprem
Version: 0.1.0
Summary: 
Home-page: https://framagit.org/roipoussiere/miprem
License: MIT
Keywords: profile merit,majority judgment,democracy
Author: Nathanaël Jourdane
Author-email: roipoussiere@protonmail.com
Requires-Python: >=3.7,<4.0
Classifier: License :: OSI Approved :: MIT License
Classifier: Programming Language :: Python :: 3
Classifier: Programming Language :: Python :: 3.7
Requires-Dist: cairosvg (>=2.4,<3.0)
Requires-Dist: colorclass (>=2.2,<3.0)
Requires-Dist: lxml (>=4.5,<5.0)
Requires-Dist: terminaltables (>=3.1,<4.0)
Project-URL: Repository, https://framagit.org/roipoussiere/miprem.git
